[{"correct":true,"key":"Kunde_Produkt_cn_cn"},{"correct":true,"key":"Atom_Elektron_n_n"},{"correct":true,"key":"Weibchen_M채nnchen_c_c"},{"correct":true,"key":"App_Kategorie_n_cn"},{"correct":false,"key":"Mitarbeiter_Mitarbeiter_1_n"},{"correct":true,"key":"Namensschild_Teilnehmer_1_c"},{"correct":true,"key":"B체rger_Partei_c_n"},{"correct":true,"key":"Planet_Mond_cn_1"},{"correct":true,"key":"Haus_Eigent체mer_n_n"},{"correct":true,"key":"Person_Person_c_c"},{"correct":true,"key":"Atom_Atomkern_1_1"},{"correct":true,"key":"Wald_Baum_n_c"},{"correct":true,"key":"Verein_Kontaktperson_1_n"},{"correct":true,"key":"Buch_Seite_n_1"},{"correct":true,"key":"Firma_Auftrag_cn_1"},{"correct":true,"key":"Sprache_Dozent_cn_n"},{"correct":true,"key":"Absender_Brief_n_c"},{"correct":true,"key":"Weinflasche_Weinsorte_c_cn"},{"correct":true,"key":"Elternteil_Mutter_Vater_t_d"},{"correct":true,"key":"Patient_Patientenakte_1_1"},{"correct":true,"key":"Haltestelle_Haltestelle_cn_cn"},{"correct":true,"key":"Schauspieler_Regisseur_Produzent_Buchautor_cn_cn_cn_cn"},{"correct":true,"key":"X-Chromosom_Y-Chromosom_c_c"},{"correct":true,"key":"Topf_Deckel_c_1"},{"correct":true,"key":"Haus_Aufzug_c_1"},{"correct":true,"key":"Vater_Mutter_Kind_n_n_1"},{"correct":true,"key":"Person_Besucher_Patient_Personal_t_n"},{"correct":true,"key":"Insekt_Fl체gel_c_cn"},{"correct":true,"key":"Mitarbeiter_Aufgabe_cn_c"},{"correct":true,"key":"Haustier_Hund_Katze_p_d"},{"correct":true,"key":"Bahnhof_Stadt_1_cn"}]